{"titulo":"El silencio","imagen":"https://m.media-amazon.com/images/I/41hA7jmev7L.jpg","descripcion":"Domingo de la Super Bowl. Año 2022. Cinco amigos han quedado para cenar en un apartamento en Manhattan. Una profesora de Física jubilada, su esposo y su exalumno esperan a la pareja que se unirá a ellos tras un accidentado vuelo desde París. La conversación abarca desde las apuestas deportivas hasta el bourbon y el manuscrito de 1912 de Einstein sobre la teoría de la relatividad. De pronto, un apagón deja al mundo a oscuras y las conexiones digitales que han marcado nuestras vidas se cortan.\nDon DeLillo completó esta novela pocas semanas antes del advenimiento de la Covid-19. El silencio es la historia de una catástrofe diferente y una vuelta de tuerca al poshumanismo como tema central de su obra: si ya habíamos asimilado la tecnología como una parte esencial del ser humano, ¿qué queda de nosotros, de nuestra identidad, si nos vemos obligados a renunciar a ella?\nDesde el asesinato de Kennedy hasta el 11-S, DeLillo ha sabido reflejar en sus novelas los hechos que han marcado cada momento histórico. El silencio describe una sociedad cuya mayor amenaza ha dejado de ser algo tangible para convertirse en un enemigo invisible, ya sea una pandemia, un ataque informático o el caos financiero.\n","link_init":"https://amazon.com/-/es/dp/B08NWFTJ31/ref=sr_1_724","link_final":"https://www.amazon.com/hz/audible/mlp/mfpdp/B08NWFTJ31?actionCode=AMSTM1450129210001"}