{"titulo":"La filosofía en el tocador","imagen":"https://m.media-amazon.com/images/I/51HdrNTQWtL.jpg","descripcion":"Considerada originalmente como una novela pornográfica, La filosofía en el tocador ha sido también interpretada como una obra de comentario socio-político. Marqués de Sade narra la historia de una niña de quince años que a petición de su padre, es instruida por partidarios del libertinaje en cómo perder todas las enseñanzas provenientes de la virtud. De Sade critica en este texto a la postura de los franceses post-monárquicos frente a la religión y la moralidad, postulando que si no se pierden estos elementos innecesarios y dañinos hacia la condición humana, Francia caerá nuevamente en las manos de la monarquía.  Atrévete a escuchar esta escalofriante novela escrita por el filósofo francés en el cual se origina la palabra sadismo.\nEl Marqués de Sade era un miembro de la nobleza francesa, político, filósofo y escritor. Muchos de los textos atribuidos a él fueron publicados en anonimato, e incluyen novelas, cuentos cortos, diálogos y obras de teatro. Su estilo se caracterizaba por desarrollar pláticas filosóficas y socio-políticas a través de la pornografía, y sus tramas generalmente incluían violencia, tortura, actos criminales y blasfemias hacia el cristianismo. De Sade proclamaba ser un partidario del libertinaje, una filosofía descrita como hedonismo extremo, en que nada en la vida tiene valor si no se puede utilizar para brindar placer, aun cuando se pongan en riesgo la moralidad y la sociedad.\n","link_init":"https://amazon.com/-/es/dp/B08FT8VN1T/ref=sr_1_254","link_final":"https://www.amazon.com/hz/audible/mlp/mfpdp/B08FT8VN1T?actionCode=AMSTM1450129210001"}