{"titulo":"El Jarama","imagen":"https://m.media-amazon.com/images/I/51e1+qDKnXL.jpg","descripcion":"Galardonada con el Premio Nadal y el Premio Nacional de la Crítica, El Jarama constituye uno de los hitos fundamentales de la narrativa española del siglo XX. \nAhora la puedes disfrutar en audiolibro.\nEscucha El Jarama, hito de la novela española de la posguerra, paradigma del objetivismo que causaba furor en aquellos años, y detonante de la llamada «novela social», que fue escrita por su autor con el sólo propósito de reflejar el habla de sus personajes. Bajo la aparente inanidad de su argumento - las conversaciones de un grupo de jóvenes madrileños que han ido a pasar un domingo del mes de agosto a orillas del río Jarama- se han reconocido todo tipo de significaciones: desde una poética reflexión sobre el paso del tiempo hasta un interpelador retrato de la España del momento. Con su misterioso encanto, la novela nunca ha perdido, desde su aparición, el favor de los lectores.\n","link_init":"https://amazon.com/-/es/El-Jarama-audiolibro/dp/B07VHS5BCF/ref=sr_1_514","link_final":"https://www.amazon.com/hz/audible/mlp/mfpdp/B07VHS5BCF?actionCode=AMSTM1450129210001"}