{"titulo":"La Tortuga Gigante: Y sus Leyes Universales (Relatos Famosos y Leyes Universales nº 2)","imagen":"https://m.media-amazon.com/images/I/61PIjGZPHCL.jpg","descripcion":"La Serie \"Relatos Famosos y Leyes Universales\" es una recopilación de cuentos famosos, traducidos y adaptados al español, cuya misión consiste en vincular \"la esencia\" de cada uno de estos eternos relatos, con las Leyes Universales y Valores Supremos que rigen, desde el campo espiritual, la vida de los seres humanos; y lograr, si no una enseñanza, al menos una conciencia más clara de cómo se manifiestan en cada una de las experiencias humanas, tanto de ficción como reales, las pautas más puras de nuestro Cosmos. Es muy posible que el lector ya haya leído estos famosos relatos; pero es nuestro deseo que pueda ahora releerlos desde otra perspectiva, la de las Leyes Universales, que a todos nos atañen, que a todos nos influyen y pro-mueven. \n","link_init":"https://amazon.com/-/es/La-Tortuga-Gigante-audiolibro/dp/B01C4UR344/ref=sr_1_485","link_final":"https://www.amazon.com/hz/audible/mlp/mfpdp/B01C4UR344?actionCode=AMSTM1450129210001"}