{"titulo":"Isadora Moon se mete en un lío (Isadora Moon 5) [Isadora Moon Gets in Trouble (Isadora Moon, Book 5)]","imagen":"https://m.media-amazon.com/images/I/51AO1MtaCFS.jpg","descripcion":"Mitad hada, mitad vampiro ¡y totalmente única!\n¡Acompaña a Isadora Moon en el día de «Trae tu mascota al colegio»!\nIsadora Moon es especial porque es diferente.\nSu mamá es un hada, su papá un vampiro y ella tiene un poquito de los dos. Cuando llega el día de «Trae tu mascota al colegio» Isadora quiere llevar a Pinky, pero su prima mayor Mirabelle tiene un plan mejor....\n¿Por qué no llevar un dragón? ¿Qué podría salir mal?\nCon una heroína única, «Isadora Moon» es una encantadora y divertida serie ideal para jóvenes lectores que quieren flores y purpurina, pero a los que también les atrae el mundo misterioso de los vampiros.\nPlease note: This audiobook is in Spanish. \n","link_init":"https://amazon.com/-/es/dp/B094LBZVDZ/ref=sr_1_493","link_final":"https://www.amazon.com/hz/audible/mlp/mfpdp/B094LBZVDZ?actionCode=AMSTM1450129210001"}