{"titulo":"Manejo de la Ira [Anger Management]: 10 Poderosos Pasos Para Tomar el Control Completo de sus Emociones, Para Hombres y Mujeres, Guía de Autoayuda Para el Autocontrol, Psicología Detras de la Ira. Incluso Para Padres.","imagen":"https://m.media-amazon.com/images/I/41qYx06fZtL.jpg","descripcion":"¿Qué es la ira? ¿Por qué la ira lleva a muchas personas a un comportamiento agresivo y poco saludable?\n¿Tiene efectos fisiológicos y psicológicos adversos?\n¿Podemos calificar toda la ira de negativa?\n¿Se siente muy irritable o con los nervios de punta?\n¿Los atascos le hacen enfadar?\n¿Sus compañeros de trabajo o su jefe le hacen enfadar con facilidad?\nLa ira no tratada y no controlada puede tener efectos muy adversos en su salud física, mental y emocional. Puede pasarle factura a usted y a las personas que le rodean. La ira también puede afectar a sus relaciones, su carrera, su vida familiar, e incluso su estilo de vida en general.\nEn la mayoría de los casos, reprimimos la ira con la esperanza de que no nos afecte a nosotros ni a nuestras relaciones, pero esa no es una forma eficaz de afrontarla. No puede ignorar la emoción de la ira para siempre: En un momento dado, le afectará. Lo mejor es que la reconozca, la aceptes y la afronte. Póngase en una posición en la que la ira no dirija su vida. Aprenda a utilizar la energía que le proporciona de forma positiva.\nEste audiolibro le ayudará a entender la ira, le guiará para identificar los desencadenantes de la misma y aprenderá a gestionarla. Gestionar la ira puede ser muy complicado si no se tienen las pautas adecuadas. Para ello, este audiolibro utiliza un lenguaje sencillo para explicar las formas útiles y no útiles de la ira. También describe los pasos que se pueden seguir para gestionarla.\nEn el interior, encontrará:\n\n","link_init":"https://amazon.com/-/es/dp/B09MV4ZHWL/ref=sr_1_385","link_final":"https://www.amazon.com/hz/audible/mlp/mfpdp/B09MV4ZHWL?actionCode=AMSTM1450129210001"}