{"titulo":"El Misterio Del Dia De Los Inocentes (Narración en Castellano) [The Mystery of April Fools' Day]: Los Futbolisimos 11","imagen":"https://m.media-amazon.com/images/I/51eyv6NFrNL.jpg","descripcion":"Es el día de los inocentes. El día del cumpleaños de mi padre, y el peor día del año para mí. ¿Que por qué? Pues por varios motivos:Porque no me gustan las bromas. Porque tenemos que jugar un torneo con El Cerrillo, el equipo que juega más sucio de toda la Liga Intercentros, y nos van a machacar. Y porque me acabo de enterar de que el colegio tiene que vender el campo de fútbol para pagar sus deudas. Y si no podemos jugar al fútbol, ¿qué será de los Futbolísimos? \nPlease note: This audiobook is in Spanish.  \n","link_init":"https://amazon.com/-/es/dp/B08LZSGTLM/ref=sr_1_569","link_final":"https://www.amazon.com/hz/audible/mlp/mfpdp/B08LZSGTLM?actionCode=AMSTM1450129210001"}