{"titulo":"Conversaciones con Dios IV [Conversations with God IV]: Despertar a la humanidad [Wake up Humanity]","imagen":"https://m.media-amazon.com/images/I/51NUd4NMqmL.jpg","descripcion":"El último libro de la serie más vendida en el mundo: Conversaciones con Dios. El diálogo evoluciona.\nCon más de 10 millones de ejemplares vendidos y traducido a 37 idiomas, Neale Donald Walsch vuelve a compartir con nosotros esta enseñanza de cómo hay seres de consciencia superior que quieren enseñarnos a evolucionar.\nPor medio de 16 ejemplos, Walsch nos invita a adoptar cualquiera de estos comportamientos que tienen dichos seres superiores; de hacerlo, cambiaremos el rumbo de la humanidad para siempre. El universo evoluciona en todas sus dimensiones y está compuesto por seres sintientes, cada uno de ellos rodeado por una misma misión: el deseo de expresar y vivir su Naturaleza Verdadera y su Identidad Verdadera.\nEste proceso incluye reconocernos en todos los aspectos de nuestras vidas como seres físicos para después conocer y atravesar nuestra parte metafísica. Integrando ambas desde lo más profundo es la manera en la que podremos hacer el cambio, y es lo que esta conversación nos quiere compartir. Será entonces que una nueva civilización pueda vivir con verdadera conciencia, despierta. Está en nuestras manos conseguirlo.\n«No se trata de un libro escrito por mí, sino que me ha ocurrido a mí.»\n","link_init":"https://amazon.com/-/es/Conversaciones-Dios-IV-audiolibro/dp/B07ZJS7C5W/ref=sr_1_56","link_final":"https://www.amazon.com/hz/audible/mlp/mfpdp/B07ZJS7C5W?actionCode=AMSTM1450129210001"}