{"titulo":"El Libro Verde De La Bruja Solitaria [The Lone Witch Green Book]: Brujería Tradicional, Hechizos de Magia y Ejercicios Para Crear tu Libro de Las Sombras [Traditional Witchcraft, Magic Spells and Exercises to Create Your Book of Shadows]","imagen":"https://m.media-amazon.com/images/I/51V1oBjQqCS.jpg","descripcion":"Este es un libro para aprender brujería tradicional por tu cuenta. Al terminar este libro tendrás tu propio libro de las sombras, y sabrás cómo usarlo para hacer hechizos, sortilegios y conjuros. Si te interesa la brujería tradicional, la brujería celta, la brujería verde, o simplemente aprender a hacer hechizos de magia en general, dándoles tu toque personal y único, este libro puede serte de gran ayuda.\nEn sus páginas descubrirás muchos secretos de la brujería, que te ayudarán a encontrar tu camino mágico y llevar a cabo hechizos por tu cuenta. \nEste libro no pretende adoctrinar ni decir a cada cual cómo debe (o no) practicar la brujería: su cometido es hacer pensar al lector a través de las tareas planteadas.\nTan solo necesitarás una libreta, 10 minutos al día y objetos que encontrarás mayormente en la naturaleza o en tu casa.\nAlgunos de los temas sobre los que podrás leer y aprender gracias a El Libro Verde de la Bruja Solitaria son:\n\nTambién puedes comprar por separado El Libro de las Sombras de la Bruja Solitaria, de la misma autora, que es un cuaderno en blanco especial para brujas.\n","link_init":"https://amazon.com/-/es/dp/B093X2Y4JZ/ref=sr_1_77","link_final":"https://www.amazon.com/hz/audible/mlp/mfpdp/B093X2Y4JZ?actionCode=AMSTM1450129210001"}