{"titulo":"Orishas: La guía definitiva de las deidades africanas orishas y su presencia en el yoruba, la santería, el vudú y el hudú, con una explicación de la adivinación del dilogún [The Definitive Guide to the African Deities Orishas and Their Presence in Yoruba, Santeria, Voodoo and Hudú, with an Explanation of the Divination of the Dilogún]","imagen":"https://m.media-amazon.com/images/I/61fiDz2bG1L.jpg","descripcion":"Conozca a fondo a los orishas de la A a la Z\nNo está solo. Los espíritus de nuestros antepasados están con usted. Los antiguos orishas, conocidos por sus tremendos poderes, le ayudarán en su viaje por la vida. Con su Ashé a su disposición, puede obtener enormes resultados y, en última instancia, vivir una vida plena.\nEn este libro, los secretos y las alabanzas de los orishas quedan al descubierto, esperando que los lea, los digiera y los aplique. No tiene que buscar lejos las respuestas divinas. Este libro le mostrará cómo encontrar sus respuestas con facilidad.\nEn este libro, usted:\nEn el libro, encontrará verdades sobre los orishas y los pasos básicos que necesita para adorar al orisha de su elección, particularmente a los orishas mayores. Una cosa es cierta, la adoración de los orishas está destinada a influir en su vida de manera significativa, y usted puede determinar la energía (positiva o negativa) que obtiene de ellos. Hay más de lo que parece en este libro.\nAdquiera este libro ahora para aprender más sobre los orishas.\n","link_init":"https://amazon.com/-/es/dp/B09KTJRSHD/ref=sr_1_204","link_final":"https://www.amazon.com/hz/audible/mlp/mfpdp/B09KTJRSHD?actionCode=AMSTM1450129210001"}