{"titulo":"Vida después de la muerte [Life After Death]","imagen":"https://m.media-amazon.com/images/I/514MY-57VcL.jpg","descripcion":"¿EXISTE LA VIDA DESPUÉS DE LA MUERTE?\n¿HAY UN TÚNEL QUE NOS LLEVA AL MÁS ALLÁ?\n¿AL MORIR NOS REENCONTRAMOS CON NUESTROS SERES QUERIDOS QUE HAN FALLECIDO?\n¿SON REALES LAS EXPERIENCIAS CERCANAS A LA MUERTE O SON PRODUCTO DE NUESTRA IMAGINACIÓN?\nEn este volumen, Esteban Cruz reúne testimonios de personas que aseguran haber estado en las fronteras de la vida y la muerte, y han regresado con recuerdos enigmáticos y luminosos; leyendas de la cultura popular sobre espíritus y aparecidos, y registros históricos sobre lo que puede suceder después de la muerte, para que el lector saque sus propias conclusiones. El autor no pretende encontrar verdades absolutas sobre el más allá, sino presentar, con rigor periodístico, varias de las posturas que existen alrededor de este tema. Todas las experiencias cercanas a la muerte relatadas en este libro son muy distintas entre sí, pero tienen un punto en común: los entrevistados coinciden en que después de la vida existe un camino plácido y esperanzador.\nIncluye testimonios de Ernesto Samper Pizano, J. J. Benítez, Antonio Navarro Wolff, Juan Manuel Correal y Fabiola Posada, entre otros.\n","link_init":"https://amazon.com/-/es/dp/B09VSC7291/ref=sr_1_275","link_final":"https://www.amazon.com/hz/audible/mlp/mfpdp/B09VSC7291?actionCode=AMSTM1450129210001"}