{"titulo":"Atención Plena: Mindfulness basado en la tradición budista","imagen":"https://m.media-amazon.com/images/I/414gImU+G9S.jpg","descripcion":"Este manual basado en la tradición budista de Dokushô Villalba Roshi, auténtico maestro zen contemporáneo, nos presenta la esencia de la experiencia del despertar del Buda: la atención plena (mindfulness). Usando un lenguaje contemporáneo, nos propone descubrirla y cultivarla siguiendo un método adaptado a nuestra vida cotidiana. El libro forma parte de un ecosistema educativo que hace que su método de capacitación integral sea accesible para todos, pues satisface tres necesidades esenciales: presenta una espiritualidad secular, humanista y universal, adecuada para todos. En lo más profundo de sus múltiples expresiones, el despertar espiritual es uno y su cimiento es el estado de atención plena, abierta y compasiva. Cultiva la armonía, alivia el estrés y la distracción emocional moderna. Nos ayuda a reconectar con la naturaleza y a poder vivir la no violencia que respeta \"al otro\", al entorno y a nosotros mismos.\n","link_init":"https://amazon.com/-/es/dp/B0953VMXL5/ref=sr_1_788","link_final":"https://www.amazon.com/hz/audible/mlp/mfpdp/B0953VMXL5?actionCode=AMSTM1450129210001"}