{"titulo":"La tía Cósima [Aunt Cosima]","imagen":"https://m.media-amazon.com/images/I/51MgZiRD7xL.jpg","descripcion":"Puede el amor regalar una segunda oportunidad? \nCósima es una mujer en la plenitud de la vida. Psicóloga de profesión y especializada en el tratamiento del autismo infantil, posee una fundación de enorme prestigio, donde se respira un ambiente cuidado y buen humor. Allí trabaja con perros especialmente adiestrados para ayudar a los niños con alguna condición del espectro autista. Es feliz con su trabajo, con sus amigos y sus sobrinos, a quienes dedica los pocos ratos libres de que dispone.\nEn su adolescencia, sin embargo, padeció la crueldad de algunos compañeros de escuela, experiencia que la marcó profundamente, al tiempo que le sirvió para convertirse en la mujer comprometida que es hoy.\nSi bien esa etapa de sufrimiento quedó atrás, un día irrumpe de nuevo para ofrecerle algo que quizá deseaba: un amor inesperado, una pasión que la desborda, un abismo de sorpresa e incertidumbre. ¿Podrá ese amor reparar el daño que no se olvida? ¿Podrá deshacer la vergüenza, la frustración y el enojo?\nCon su nueva novela, Florencia Bonelli logra otra vez el misterio de la devoción lectora con una historia que perdura más allá de la último momento. \nPlease note: This audiobook is in Spanish. \n","link_init":"https://amazon.com/-/es/dp/B08PL357B8/ref=sr_1_49","link_final":"https://www.amazon.com/hz/audible/mlp/mfpdp/B08PL357B8?actionCode=AMSTM1450129210001"}