{"titulo":"Los Rescatadores Mágicos en el campamento pirata: Los Rescatadores Mágicos 4","imagen":"https://m.media-amazon.com/images/I/61ajnnRMrRL.jpg","descripcion":"¡Por fin llegó el verano! Mientras los Rescatadores Mágicos se bañan en la piscina de Zoe, reciben un mensaje urgente de Imaginaria. ¡Los piratas y las sirenas están peleados!\nLos únicos que pueden devolver la paz son los tres amigos, pero no será nada fácil. Primero tendrán que aprender a ser piratas y sirenas para ponerse en su lugar.\nAl comprar este título, el archivo PDF que lo acompaña estará disponible en su confirmación de compra enviada por correo electrónico, así como en su biblioteca, desde su ordenador.\n","link_init":"https://amazon.com/-/es/dp/B08TMVXVCG/ref=sr_1_782","link_final":"https://www.amazon.com/hz/audible/mlp/mfpdp/B08TMVXVCG?actionCode=AMSTM1450129210001"}