{"titulo":"Millones de dólares falsos","imagen":"https://m.media-amazon.com/images/I/518BrY-zieL.jpg","descripcion":"\"Mantente casada conmigo durante un año, gánate cinco millones de dólares y sigue tu camino. Tengo una mansión, apenas nos veremos; y no te preocupes, no me interesa ser el primero\".\nCuando el presidente ejecutivo y multimillonario Asher Davis me dijo estas palabras, me quedé pasmada. Es rico e increíblemente guapo. Un tirano de día y un playboy de noche.\nOdio su sonrisa triunfante, pero al mismo tiempo su mirada seductora me hace temblar. Y ahora es mi dueño. Soy periodista, y antes falsificaba mi identidad a menudo para tener acceso a las fiestas más exquisitas; pero tenía que ser él, de todas las personas, el que me atrapara.\nEra una bendición disfrazada: Asher necesita una esposa falsa para cerrar el mayor negocio de su carrera con un individuo que se postula para presidente. Así que tengo que elegir entre ser demandada, arruinar mi carrera e ir a la cárcel, o casarme con él por un año y embolsar 5 millones de dólares. Fácil, ¿verdad?\nBueno, eso pensé. Pero lo que comienza como una falsedad, de repente se convierte en algo muy intenso. No solo pasamos una noche apasionada y le hago el regalo de ser el primero. Peor aún, olvidé que me juré a mí misma que nunca me enamoraría del enemigo. ¡Y como si eso fuera poco, mis náuseas matutinas me dicen que una sorpresa inesperada está en camino!\nCuando descubro el espantoso secreto del socio comercial de Asher, tengo que elegir a que renunciar: mi amor por Asher y nuestro bebé por nacer, 5.000.000 de dólares o mi integridad...\nReservado para adultos.\n","link_init":"https://amazon.com/-/es/dp/B09N3KKXMX/ref=sr_1_883","link_final":"https://www.amazon.com/hz/audible/mlp/mfpdp/B09N3KKXMX?actionCode=AMSTM1450129210001"}