{"titulo":"Fuego de una Noche [Fire of a Night]","imagen":"https://m.media-amazon.com/images/I/51BL0Jg0pES.jpg","descripcion":"Eres un problema, ¿lo sabías?El capitán de bomberos Cameron McClain cree que yo soy la entrometida, pero él es el instigador. Su aspecto robusto, su seguridad y su sentido del humor deberían ser ilegales. Sin mencionar esos hoyuelos.Ellos son en parte culpables de que me vaya de la fiesta y lo siga a su habitación. Sabía que teníamos química, pero desde el momento en que sus labios tocan los míos, mi cuerpo se enciende. Solo basta con un toque para que la atracción entre nosotros se convierta en un infierno innegable.Fuego de una noche. Era todo lo que estábamos destinados a ser. Pero ahora que sé lo bueno que es estar juntos, ¿cómo puedo mantenerme alejada de él?\n","link_init":"https://amazon.com/-/es/dp/B097NF54BQ/ref=sr_1_904","link_final":"https://www.amazon.com/hz/audible/mlp/mfpdp/B097NF54BQ?actionCode=AMSTM1450129210001"}