{"titulo":"Garoé","imagen":"https://m.media-amazon.com/images/I/51e62jSvB0L.jpg","descripcion":"Una misteriosa leyenda envuelve a la isla canaria de El Hierro. Sus habitantes guardan un secreto que les ha permitido enfrentarse a muchos peligros a lo largo de toda la historia. Sin embargo, la corona española está a punto de descubrir ese secreto. El general Gonzalo Baeza ha sido enviado allí para descubrirlo, pero se enamora de la nativa bimbache llamada Garza. Su historia de amor estará salpicada por el tráfico de esclavos, la conquista de El Hierro, la tragedia y el secreto mejor guardado de la isla.\n","link_init":"https://amazon.com/-/es/dp/B08G18L7T3/ref=sr_1_999","link_final":"https://www.amazon.com/hz/audible/mlp/mfpdp/B08G18L7T3?actionCode=AMSTM1450129210001"}