{"titulo":"Y siempre tú","imagen":"https://m.media-amazon.com/images/I/514YgJY9zHL.jpg","descripcion":"Han pasado más de veinte años desde que Evelyn abandonó el rancho en el que se crió para ir a la universidad. En su etapa de estudiante, conoció a un buen chico con el que se casó y empezó una nueva vida. Pero cuando una serie de acontecimientos inesperados le hacen cuestionarse su existencia, Evelyn decide regresar a casa en busca de calma. Allí volverá a sentir de nuevo la felicidad, pero, ¿será suficiente para curar sus heridas?\nSe aficionó desde pequeña a los cómics de Marvel y DC y más tarde se interesó por el anime, la literatura y la escritura. Comenzó escribiendo pequeños relatos y de ahí pasó a la novela. Suele cultivar la literatura romántica, \"new adult\" y la fantasía.\n","link_init":"https://amazon.com/-/es/dp/B09HTRZ8RY/ref=sr_1_1186","link_final":"https://www.amazon.com/hz/audible/mlp/mfpdp/B09HTRZ8RY?actionCode=AMSTM1450129210001"}