{"titulo":"Teoría del apego y enfermedad mental [Attachment Theory and Mental Illness]","imagen":"https://m.media-amazon.com/images/I/51AjcKnG+QL.jpg","descripcion":"El principio básico de la teoría del apego es que los apegos emocionales de una persona influyen en las formas en que el individuo trata las situaciones problemáticas. Y la forma en que uno maneja situaciones problemáticas influye en las relaciones de la persona con los demás. Este audiolibro explica qué es la teoría del apego y cómo las enfermedades mentales en adultos, incluidos los problemas de relación, pueden explicarse en términos de la misma.\n","link_init":"https://amazon.com/-/es/Teoria-apego-enfermedad-mental/dp/B086P6GLM2/ref=sr_1_1116","link_final":"https://www.amazon.com/hz/audible/mlp/mfpdp/B086P6GLM2?actionCode=AMSTM1450129210001"}