{"titulo":"Ciencia de Datos para Empresas [Data Science for Companies]","imagen":"https://m.media-amazon.com/images/I/51sCOnLtvbL.jpg","descripcion":"¿Quiere aprender sobre la Ciencia de Datos, pero no está de humor para leer un libro de texto aburrido?\nEste audiolibro de Ciencia de Datos podría ser la respuesta que está buscando...\nLa Ciencia de Datos tiene un gran impacto en la forma en que las empresas hacen negocios, y aquellos que no aprenden sobre este campo revolucionario podrían quedarse atrás.\nVerá, la ciencia de los datos le ayudará a tomar mejores decisiones, conocer qué productos y servicios lanzar y cómo brindar un mejor servicio a sus clientes. Y todo se hace mediante la recopilación y clasificación de una gran cantidad de información, por lo que tiene las fuentes correctas detrás de usted cuando tomas una decisión importante.\nEn esta guía, descubrirá más sobre la Ciencia de Datos y cómo comenzar en este campo.  \nEste libro abordará los siguientes temas:\n\nObtenga este libro ahora para conocer más sobre la Ciencia de Datos para empresas!\n Please note: This audiobook is in Spanish\n","link_init":"https://amazon.com/-/es/Ciencia-Datos-Empresas-audiolibro/dp/B07ND4TZBS/ref=sr_1_87","link_final":"https://www.amazon.com/hz/audible/mlp/mfpdp/B07ND4TZBS?actionCode=AMSTM1450129210001"}