{"titulo":"Un verano para olvidarte","imagen":"https://m.media-amazon.com/images/I/51PbhpkFs0S.jpg","descripcion":"Con el otoño cada vez más cerca, Caroline necesita tomar una decisión que inevitablemente romperá el corazón de alguien, pero ¿de quién?\nEl plan es el siguiente: cuando Caroline cumpla diecisiete años, ella y su novio Jake huirán de su pequeño pueblo para nunca regresar. Desde que se conocieron, Caroline siente que las paredes de su cuarto la asfixian y escapar con el amor de su vida le parece la mejor idea del planeta. Un par de meses antes de la fuga, Caroline consigue un trabajo de verano en la tienda de regalos del acuario local, donde pasa horas fantaseando sobre su nueva vida. Todo está planeado a la perfección, hasta que conoce a Georgia, una guía del campamento del acuario que cambiará su vida.\nEntre almuerzos con pizza, viajes a parques de diversiones y pláticas nocturnas, Georgia le muestra a Caroline que no todo gira alrededor de Jake. Mientras la relación de Georgia y Caroline se vuelve más fuerte, los planes de Caroline para irse se vuelven confusos, y eso tiene a Jake de un humor terrible que amenaza su relación y su futuro.\n","link_init":"https://amazon.com/-/es/dp/B0979GCDVK/ref=sr_1_546","link_final":"https://www.amazon.com/hz/audible/mlp/mfpdp/B0979GCDVK?actionCode=AMSTM1450129210001"}