{"titulo":"Francés. Gramática Fácil [French. Easy Grammar]: Mejora tu fluidez hablando francés [Improve Your Fluency Speaking French]","imagen":"https://m.media-amazon.com/images/I/51poQe25UwL.jpg","descripcion":"Francés. Gramática fácil es un audio que recopila los aspectos clave de la gramática francesa, desde lo más básico hasta lo más avanzado. Sus 180 lecciones se distribuyen a lo largo de tres distintos niveles: básico, intermedio y avanzado. Siguiendo el procedimiento de la metodología Vaughan, la estructura de cada lección permite familiarizarse con el aspecto esencial del tema teórico correspondiente, adquirir vocabulario nuevo, conocer útiles consejos de pronunciación y, lo más importante, poner absolutamente todo en práctica.\n","link_init":"https://amazon.com/-/es/dp/B08GVCL76T/ref=sr_1_331","link_final":"https://www.amazon.com/hz/audible/mlp/mfpdp/B08GVCL76T?actionCode=AMSTM1450129210001"}