{"titulo":"Guías HBR: Gestión de proyectos (Narración en Castellano) [HBR Guides: Project Management]","imagen":"https://m.media-amazon.com/images/I/412+LmmejIL.jpg","descripcion":"Si estás gestionando tu primer proyecto o simplemente estás cansado de improvisar, la Guía HBR Gestión de Proyectos te proporcionará las herramientas y la confianza que necesitas para definir y alcanzar objetivos inteligentes, y te enseñará a aprovechar las lecciones aprendidas para mejorar el desarrollo de futuros proyectos. Esta guía te ayudará a formar equipos potentes y motivados, a organizar los principales objetivos en tareas manejables, a crear un calendario de trabajo para mantener todo bajo control, a evaluar el progreso hacia tus objetivos, a gestionar las expectativas de las partes interesadas y a poner punto final a tu proyecto y medir su éxito.\nPlease note: This audiobook is in Castilian Spanish.\n","link_init":"https://amazon.com/-/es/dp/B09KY9WLNK/ref=sr_1_505","link_final":"https://www.amazon.com/hz/audible/mlp/mfpdp/B09KY9WLNK?actionCode=AMSTM1450129210001"}