{"titulo":"Emprender un negocio [Start a Business]: Paso a paso para principiantes [Step by Step for Beginners]","imagen":"https://m.media-amazon.com/images/I/51ijplCJ-aL.jpg","descripcion":"Probablemente haya leído innumerables historias de éxito sobre personas que han iniciado negocios en todo el mundo. Si este es un objetivo que usted también tiene en mente, está dando el paso correcto al utilizar este libro como guía.\nCon todas las maravillosas ideas que ha estado desarrollando, finalmente es el momento de ser más proactivo. Usted va a aprender exactamente lo que se necesita para iniciar su propio negocio. No sólo entenderá lo que debe hacer para ponerlo en marcha, sino que también descubrirá muchos consejos útiles que le seguirán ayudando a lo largo del camino.\n","link_init":"https://amazon.com/-/es/dp/B09DFPMQR2/ref=sr_1_572","link_final":"https://www.amazon.com/hz/audible/mlp/mfpdp/B09DFPMQR2?actionCode=AMSTM1450129210001"}