{"titulo":"Como Ganar Reclamos Menores en la Corte y Cobrar? [How to Win in Small Claims Court and Collect]","imagen":"https://m.media-amazon.com/images/I/51jANKqoQHL.jpg","descripcion":"El Autor, productor y editor Dr. Mickey Frazier, Sr., explica un plan orientado a la acción simple para la recuperación de daños monetarios a través del sistema de la corte de reclamos menores. A través de sus estudios detalla batallas contra los individuos, pequeñas empresas y grandes corporaciones, Mickey ofrece orientación lógica racional que le ahorrará tiempo y frustración en la recuperación de su dinero. Usted les ha hecho saber verbalmente o por medio escrito que está demandando y ha sido todo en vano, así que es hora de luchar. La corte de reclamos menores nos permite luchar y jugar el juego de una manera grande, cualquier persona puede recibir una compensación monetaria si usted utiliza el sistema de corte de reclamos menores. Les recordaré en lo largo de todo mi libro, que los estados varían en muchos aspectos del sistema, incluidos los tribunales que se ocupan de los casos. Algunos estados lo llaman \"Tribunal Popular\", otros lo llaman \"Tribunal de Distrito.\" y algunos lo llaman \"la Corte del Condado.\" Se le puede llamar igualmente \"Tribunal de Circuito\", \"Tribunal Municipal\", \"juez de la Corte\", \"Magistrado Corte\" o \"juez de paz\". Independientemente de la variación, significa \"La corte de reclamos menores.\" \nPlease note: This audiobook is in Spanish. \n","link_init":"https://amazon.com/-/es/Como-Ganar-Reclamos-Menores-Corte-Cobrar/dp/B01975JJFK/ref=sr_1_935","link_final":"https://www.amazon.com/hz/audible/mlp/mfpdp/B01975JJFK?actionCode=AMSTM1450129210001"}