{"titulo":"Yukako","imagen":"https://m.media-amazon.com/images/I/51zA+DlQQbL.jpg","descripcion":"\"Christian estaba convencido de que sería capaz de dominarla y Yukako dejó que siguiera con aquella mentira; le divertía jugar con él. Le gustaba hacerle creer que porque tuviera un cuerpo musculoso y en forma de alguna manera significaba que sería ella quien acabara atada al crucifijo. Inocencia juvenil contra una mujer experimentada. Yukako sonrió al pensar en lo que tenía planeado para él. Su plan era que él se arrastrara voluntariamente hacia la cruz y le rogara que lo atara. Eso sí, esperaba que tuviera más resistencia que el resto de hombres con los que había estado.\"\nDespués del fallecimiento de su compañero Michael y una larga etapa de duelo, Yukako vuelve a reconectar con su libertad sexual a través de látigos y otros juguetes sexuales en Delirium, un espacio seguro para los y las amantes del placer y el dolor.\nEn sus obras, Sandra Norrbin permite que la sexualidad femenina sea el centro de atención, independientemente de las reglas y expectativas de la sociedad. A través de su amplia red de contactos en las comunidades BDSM y swingers, nunca faltan ideas para nuevos relatos eróticos.\nReservado para adultos.\n","link_init":"https://amazon.com/-/es/dp/B09N8WP9YW/ref=sr_1_416","link_final":"https://www.amazon.com/hz/audible/mlp/mfpdp/B09N8WP9YW?actionCode=AMSTM1450129210001"}