{"titulo":"Un sueño en París","imagen":"https://m.media-amazon.com/images/I/41gQscTg4EL.jpg","descripcion":"\"Cuando llego a la última esquina del mapa, un gigantesco edificio se cierne sobre mí. Este es el lugar, la dirección que me dio hace unos días. Que yo esté aquí es una locura. Lo he dejado todo y he venido. Nadie lo sabe\".\nGabriella y Alfons se desean desde sus años de universidad. Las circunstancias de la vida han hecho que su deseo jamás se haya materializado, pero el paso de los años no ha borrado su conexión. Hoy, con París como testigo, se verán de nuevo y podrán, por fin, vivir ese momento que tantas veces han soñado.\nAmanda Backman es una autora sueca. Además de escribir manuscritos y poemas, trabaja como editora independiente en el mundo editorial Suecia.\nReservado para adultos.\n","link_init":"https://amazon.com/-/es/dp/B09MYYNXMG/ref=sr_1_464","link_final":"https://www.amazon.com/hz/audible/mlp/mfpdp/B09MYYNXMG?actionCode=AMSTM1450129210001"}