{"titulo":"Cosas de Japón","imagen":"https://m.media-amazon.com/images/I/51wT0pYxZIL.jpg","descripcion":"Un curioso y atractivo repaso por la cultura tradicional y contemporánea japonesa en forma de diccionario, que nos presenta un recorrido pormenorizado por el Japón de la antigüedad y por la rabiosa actualidad de una de las culturas más influyentes del presente. En este viaje descubriremos desde el origen los kimonos hasta los pasos de la ceremonia del té o los pormenores de la arquitectura japonesa. Imprescindible para quienes siempre han sentido fascinación por Japón y para quienes deseen un buen punto de partida para empezar a entender su cultura.\nEste audiolibro está narrado en castellano.\nBasil H. Chamberlain fue un viajero y empresario nacido en Portsmouth en 1850 y fallecido en Ginebra en 1935. Banquero de formación, una crisis nerviosa lo llevó a abandonar su empleo y a viajar por el mundo. Acabó en Japón, lugar donde impartió clases y trabajó como traductor. Recogió toda su sabiduría en la obra cumbre Cosas de Japón.\n","link_init":"https://amazon.com/-/es/dp/B0BHYV9YL2/ref=sr_1_972","link_final":"https://www.amazon.com/hz/audible/mlp/mfpdp/B0BHYV9YL2?actionCode=AMSTM1450129210001"}