{"titulo":"Atila el Huno: Una guía fascinante del gobernante de los hunos y sus invasiones del imperio romano","imagen":"https://m.media-amazon.com/images/I/51keKt-5VzS.jpg","descripcion":"Si quiere descubrir la fascinante historia de Atila el Huno, siga leyendo...\nEn la imaginación popular, Atila el Huno es uno de los líderes más bárbaros de la historia. Sus guerreros tienen la reputación de ser despiadados, crueles y estar sedientos de sangre. Además, se cree que los hunos son salvajes carentes de cualquier sentido de cultura civilizada.\nLos hunos violaban y saqueaban cada vez que les surgía la oportunidad. Sus incursiones en tierras que estaban mal protegidas durante el desmoronamiento del Imperio romano se convirtieron en legendarias. Se cree que los hunos bajo el mando de Atila han sido en gran parte responsables del colapso del Imperio romano y del comienzo de la Edad Oscura en Europa.\nEn Atila el Huno: Una guía fascinante del gobernante de los hunos y sus invasiones del Imperio romano, descubrirá temas como:   \n\n¡Obtenga este libro ahora para aprender más acerca de Atila el Huno!\n","link_init":"https://amazon.com/-/es/dp/B093TX85DW/ref=sr_1_1084","link_final":"https://www.amazon.com/hz/audible/mlp/mfpdp/B093TX85DW?actionCode=AMSTM1450129210001"}