{"titulo":"En mi casa no entra un gato [No Cat Enters My House]","imagen":"https://m.media-amazon.com/images/I/51lbYfo0bWL.jpg","descripcion":"Las aventuras y desventuras de un gatuno primerizo \nPedro pertenecía hasta hace poco al grupo de la Resistencia Gatuna, formado por todas aquellas personas que sin pudor decían «en mi casa no entra un gato, y punto». Hasta que un día conoció a Mía, una gatita blanca y parda que se instala en su piso y no solo se adueña del espacio, sino que también conquista su corazón. Pedro no podía imaginar hasta qué punto Mía iba a cambiar su vida. Divertidas, desenfadadas y emotivas, estas memorias gatunas desvelan todos los entresijos del mundo de los gatos. Y mucho más. Porque, en realidad, ¿quién no ha sido primerizo alguna vez? \nPlease note: This audiobook is in Spanish. \n","link_init":"https://amazon.com/-/es/dp/B08W8BMSBM/ref=sr_1_97","link_final":"https://www.amazon.com/hz/audible/mlp/mfpdp/B08W8BMSBM?actionCode=AMSTM1450129210001"}